PyTwitchInteract-1.0.6.dist-info/DESCRIPTION.rst
PyTwitchInteract-1.0.6.dist-info/METADATA
PyTwitchInteract-1.0.6.dist-info/RECORD
PyTwitchInteract-1.0.6.dist-info/WHEEL
PyTwitchInteract-1.0.6.dist-info/metadata.json
PyTwitchInteract-1.0.6.dist-info/top_level.txt
pytwitchinteract/__init__.py
pytwitchinteract/twitch.py
pytwitchinteract/chat/__init__.py
pytwitchinteract/chat/chat.py
pytwitchinteract/models/__init__.py
pytwitchinteract/models/follow.py
pytwitchinteract/models/game.py
pytwitchinteract/models/stream.py
pytwitchinteract/models/streammetadata.py
pytwitchinteract/models/user.py
pytwitchinteract/models/video.py
pytwitchinteract/utils/__init__.py
pytwitchinteract/utils/pagination.py
