Metadata-Version: 2.0
Name: PyTwitchInteract
Version: 1.0.6
Summary: A collection of tools and utilities for easier interaction with Twitch.
Home-page: https://github.com/Vilsol/PyTwitchInteract
Author: Vilsol
Author-email: me@vil.so
License: UNKNOWN
Platform: UNKNOWN
